algomol/algomol_core.cpython-312-darwin.so
algomol/libalgomol.dylib
algomol/__init__.py
algomol-0.0.3.post4.dist-info/RECORD
algomol-0.0.3.post4.dist-info/WHEEL
algomol-0.0.3.post4.dist-info/METADATA
