Metadata-Version: 2.2
Name: algomol
Version: 0.0.3.post4
Summary: A Python/C++ library for fast detection of chemical equivalent (or magnetic equivalent) atoms in molecules, useful for assigning/computing peaks in NMR spectroscopy.
Author-Email: AlgoMol LLC <lanl2vz@algomol.com>
License: Proprietary
Classifier: License :: Other/Proprietary License
Requires-Python: >=3.9
